ezinput/__init__.py
ezinput/ezinput.py
ezinput/ezinput_jupyter.py
ezinput/ezinput_prompt.py
ezinput/ipynb_runner.py
ezinput-0.0.18.dist-info/licenses/LICENSE.txt
ezinput-0.0.18.dist-info/METADATA
ezinput-0.0.18.dist-info/WHEEL
ezinput-0.0.18.dist-info/entry_points.txt
ezinput-0.0.18.dist-info/top_level.txt
ezinput-0.0.18.dist-info/RECORD
