Metadata-Version: 2.4
Name: ezinput
Version: 0.0.18
Summary: Simplify the creation of GUI elements in terminals and Jupyter Notebooks
Author-email: "Bruno M. Saraiva" <bruno.msaraiva2@gmail.com>, Ricardo Henriques <ricardo@henriqueslab.org>
License: MIT
Classifier: Programming Language :: Python :: 3.9
Classifier: License :: OSI Approved :: MIT License
Classifier: Operating System :: OS Independent
Requires-Python: >=3.9
License-File: LICENSE.txt
Requires-Dist: ipython
Requires-Dist: ipywidgets
Requires-Dist: ipyfilechooser>=0.6.0
Requires-Dist: pyyaml>=6.0.1
Requires-Dist: toml>=0.10.2
Requires-Dist: prompt-toolkit>=3.0.43
Provides-Extra: all
Requires-Dist: ezinput[dev,test]; extra == "all"
Provides-Extra: dev
Requires-Dist: pre-commit>=3.7.0; extra == "dev"
Requires-Dist: ipykernel>=6.29.4; extra == "dev"
Requires-Dist: ruff>=0.4.3; extra == "dev"
Requires-Dist: gptrepo>=1.0.3; extra == "dev"
Requires-Dist: pdoc>=12.3.1; extra == "dev"
Requires-Dist: build; extra == "dev"
Provides-Extra: test
Requires-Dist: pytest>=7.2.0; extra == "test"
Requires-Dist: pytest-xdist>=3.6.1; extra == "test"
Requires-Dist: pytest-cov>=5.0.0; extra == "test"
Requires-Dist: pytest-timeout>=2.2; extra == "test"
Requires-Dist: nbmake>=1.5.3; extra == "test"
Requires-Dist: mypy>=1.10.0; extra == "test"
Provides-Extra: colab
Requires-Dist: ipycanvas==0.11.0; extra == "colab"
Requires-Dist: ipywidgets==7.7.1; extra == "colab"
Dynamic: license-file
